<annotation>
	<folder>cheetah</folder>
	<filename>chee (469).jpg</filename>
	<path>D:\animaldataset_final\cheetah\chee (469).jpg</path>
	<source>
		<database>Unknown</database>
	</source>
	<size>
		<width>612</width>
		<height>407</height>
		<depth>3</depth>
	</size>
	<segmented>0</segmented>
	<object>
		<name>cheetah</name>
		<pose>Unspecified</pose>
		<truncated>0</truncated>
		<difficult>0</difficult>
		<bndbox>
			<xmin>248</xmin>
			<ymin>12</ymin>
			<xmax>405</xmax>
			<ymax>204</ymax>
		</bndbox>
	</object>
</annotation>
