<annotation>
	<folder>panda</folder>
	<filename>panda (205).jpg</filename>
	<path>D:\animaldataset_final\panda\panda (205).jpg</path>
	<source>
		<database>Unknown</database>
	</source>
	<size>
		<width>410</width>
		<height>612</height>
		<depth>3</depth>
	</size>
	<segmented>0</segmented>
	<object>
		<name>panda</name>
		<pose>Unspecified</pose>
		<truncated>0</truncated>
		<difficult>0</difficult>
		<bndbox>
			<xmin>123</xmin>
			<ymin>54</ymin>
			<xmax>403</xmax>
			<ymax>361</ymax>
		</bndbox>
	</object>
</annotation>
